[{"typ":"dir","name":"UI组件","path":"UI组件","items":[{"typ":"file","name":"01-开发规范和建议","path":"UI组件/01-开发规范和建议.md","updateAt":1680264175430.1282,"items":[],"icon":"explore"}],"updateAt":0,"dirInfo":{"id":4,"icon":{"pkg":"mdi","type":"filled","name":"hive"},"baseName":"UI组件"}},{"typ":"dir","name":"使用","path":"使用","items":[{"typ":"file","name":"1-组件","path":"使用/1-组件.md","updateAt":1683769799154.9463,"items":[],"icon":{"name":"explore"},"id":1},{"typ":"file","name":"2-数据","path":"使用/2-数据.md","updateAt":1683762848714.2422,"items":[],"icon":{"name":"explore"},"id":2},{"typ":"file","name":"3-事件","path":"使用/3-事件.md","updateAt":1683762860673.0955,"items":[],"icon":{"name":"explore"},"id":3},{"typ":"file","name":"4-条件","path":"使用/4-条件.md","updateAt":1683762885933.4214,"items":[],"icon":{"name":"explore"},"id":5},{"typ":"file","name":"5-循环","path":"使用/5-循环.md","updateAt":1683762657596.8242,"items":[],"icon":{"name":"explore"},"id":7},{"typ":"file","name":"6-样式","path":"使用/6-样式.md","updateAt":1683762893617.708,"items":[],"icon":{"name":"explore"},"id":6},{"typ":"file","name":"7-脚本","path":"使用/7-脚本.md","updateAt":1683762903444.8386,"items":[],"icon":{"name":"explore"},"id":7},{"typ":"file","name":"8-引入第三方库","path":"使用/8-引入第三方库.md","updateAt":1683762927925.0403,"items":[],"icon":{"name":"explore"},"id":8}],"updateAt":0,"dirInfo":{"id":2,"icon":{"pkg":"mdi","type":"filled","name":"auto_stories"},"baseName":"使用"}},{"typ":"dir","name":"实践","path":"实践","items":[{"typ":"file","name":"01-开发规范和建议","path":"实践/01-开发规范和建议.md","updateAt":1678152043697.4531,"items":[],"icon":"explore"}],"updateAt":0,"dirInfo":{"id":7,"icon":{"pkg":"mdi","type":"filled","name":"hive"},"baseName":"实践"}},{"typ":"dir","name":"应用","path":"应用","items":[{"typ":"file","name":"01-项目结构","path":"应用/01-项目结构.md","updateAt":1678152043740.117,"items":[],"icon":"explore"},{"typ":"file","name":"02-开发和调试","path":"应用/02-开发和调试.md","updateAt":1678152043737.1812,"items":[],"icon":"explore"},{"typ":"file","name":"03-打包和发布","path":"应用/03-打包和发布.md","updateAt":1678152043737.1812,"items":[],"icon":"explore"},{"typ":"file","name":"04-组件库","path":"应用/04-组件库.md","updateAt":1678152043699.4622,"items":[],"icon":"explore"}],"updateAt":0,"dirInfo":{"id":4,"icon":{"pkg":"mdi","type":"filled","name":"important_devices"},"baseName":"应用"}},{"typ":"dir","name":"开始","path":"开始","items":[{"typ":"file","name":"快速上手","path":"开始/快速上手.md","updateAt":1680618936790.742,"items":[],"icon":{"name":"sports_score","pkg":"mdi","type":"filled"},"id":2},{"typ":"file","name":"思考","path":"开始/思考.md","updateAt":1682048144216.501,"items":[],"icon":{"name":"lightbulb_circle","pkg":"mdi","type":"filled"},"id":4},{"typ":"file","name":"更新","path":"开始/更新.md","updateAt":1683730986657.586,"items":[],"icon":{"name":"update","pkg":"mdi","type":"filled"},"id":99},{"typ":"file","name":"欢迎","path":"开始/欢迎.md","updateAt":1681301201432.0784,"items":[],"icon":{"name":"explore","pkg":"mdi","type":"filled"},"id":1},{"typ":"file","name":"进一步扩展","path":"开始/进一步扩展.md","updateAt":1683736903462.4753,"items":[],"icon":{"name":"dashboard_customize","pkg":"mdi","type":"filled"},"id":3}],"updateAt":0,"dirInfo":{"id":1,"icon":{"pkg":"mdi","type":"filled","name":"bookmarks"},"baseName":"开始"}},{"typ":"dir","name":"扩展","path":"扩展","items":[{"typ":"file","name":"01-SVG扩展","path":"扩展/01-SVG扩展.md","updateAt":1678152043698.4639,"items":[],"icon":"explore"},{"typ":"file","name":"02-图标库","path":"扩展/02-图标库.md","updateAt":1680884386733.2988,"items":[],"icon":{"name":"explore","pkg":"mdi","type":"filled"},"id":1},{"typ":"file","name":"03-字体","path":"扩展/03-字体.md","updateAt":1678152043698.4639,"items":[],"icon":"explore"}],"updateAt":0,"dirInfo":{"id":5,"icon":{"pkg":"mdi","type":"filled","name":"hive"},"baseName":"扩展"}},{"typ":"dir","name":"技巧","path":"技巧","items":[{"typ":"file","name":"01-SEO优化","path":"技巧/01-SEO优化.md","updateAt":1677304843374.6213,"items":[]},{"typ":"file","name":"02-UI自动化测试","path":"技巧/02-UI自动化测试.md","updateAt":1677309192594.5205,"items":[]}],"updateAt":0,"dirInfo":{"id":8,"icon":{"pkg":"mdi","type":"filled","name":"hive"},"baseName":"技巧"}},{"typ":"dir","name":"资源","path":"资源","items":[{"typ":"file","name":"01-开发规范和建议","path":"资源/01-开发规范和建议.md","updateAt":1678152043697.4531,"items":[],"icon":"explore"}],"updateAt":0,"dirInfo":{"id":7,"icon":{"pkg":"mdi","type":"filled","name":"hive"},"baseName":"资源"}},{"typ":"dir","name":"进阶","path":"进阶","items":[{"typ":"file","name":"01-组件属性","path":"进阶/01-组件属性.md","updateAt":1678152043752.1892,"items":[],"icon":"explore"},{"typ":"file","name":"02-作用域","path":"进阶/02-作用域.md","updateAt":1678152043751.184,"items":[],"icon":"explore"},{"typ":"file","name":"03-原生插槽","path":"进阶/03-原生插槽.md","updateAt":1678152043751.184,"items":[],"icon":"explore"},{"typ":"file","name":"04-配色","path":"进阶/04-配色.md","updateAt":1678152043748.1858,"items":[],"icon":"explore"},{"typ":"file","name":"05-模块依赖和加载","path":"进阶/05-模块依赖和加载.md","updateAt":1678152043744.629,"items":[],"icon":"explore"},{"typ":"file","name":"06-路由","path":"进阶/06-路由.md","updateAt":1678152043743.1157,"items":[],"icon":"explore"},{"typ":"file","name":"开发和调试","path":"进阶/开发和调试.md","updateAt":1683737674634.9424,"items":[]}],"updateAt":0,"dirInfo":{"id":3,"icon":{"pkg":"mdi","type":"filled","name":"auto_stories"},"baseName":"进阶"}}]